aiopen/__about__.py
aiopen/__init__.py
aiopen/__main__.py
aiopen/_anyio.py
aiopen/core.py
aiopen/py.typed
aiopen-0.8.1.dist-info/WHEEL
aiopen-0.8.1.dist-info/METADATA
aiopen-0.8.1.dist-info/RECORD
