Metadata-Version: 2.4
Name: aiopen
Version: 0.8.1
Summary: Async file io
Keywords: aiopen,anyio,async,dgpy,fs
Author: jesse
Author-email: jesse <jessekrubin@gmail.com>
License-Expression: MIT
Classifier: Development Status :: 5 - Production/Stable
Classifier: Intended Audience :: Developers
Classifier: License :: OSI Approved :: MIT License
Classifier: Programming Language :: Python
Classifier: Programming Language :: Python :: 3 :: Only
Classifier: Programming Language :: Python :: 3.11
Classifier: Programming Language :: Python :: 3.12
Classifier: Programming Language :: Python :: 3.13
Classifier: Programming Language :: Python :: 3.14
Classifier: Typing :: Typed
Requires-Dist: funkify>=0.7
Requires-Dist: anyio>=4.4 ; extra == 'test'
Requires-Dist: pytest>=8.3.2 ; extra == 'test'
Requires-Dist: pytest-asyncio>=1 ; extra == 'test'
Requires-Python: >=3.11, <4.0
Provides-Extra: test
